AUTHORS.rst
CHANGES.rst
COPYING
MANIFEST.in
Makefile
README.rst
conftest.py
pytest.ini
setup.py
tox.ini
PyCampbellCR1000.egg-info/PKG-INFO
PyCampbellCR1000.egg-info/SOURCES.txt
PyCampbellCR1000.egg-info/dependency_links.txt
PyCampbellCR1000.egg-info/entry_points.txt
PyCampbellCR1000.egg-info/not-zip-safe
PyCampbellCR1000.egg-info/requires.txt
PyCampbellCR1000.egg-info/top_level.txt
docs/.gitignore
docs/Makefile
docs/conf.py
docs/index.rst
docs/make.bat
docs/_static/PyCampbellCR1000-fulltitle.jpg
docs/_static/PyCampbellCR1000-logo.png
docs/_templates/sidebarintro.html
pycampbellcr1000/__init__.py
pycampbellcr1000/__main__.py
pycampbellcr1000/compat.py
pycampbellcr1000/device.py
pycampbellcr1000/exceptions.py
pycampbellcr1000/logger.py
pycampbellcr1000/pakbus.py
pycampbellcr1000/utils.py
pycampbellcr1000/tests/__init__.py
pycampbellcr1000/tests/test_1_pakbus.py
pycampbellcr1000/tests/test_2_utils.py
pycampbellcr1000/tests/test_3_device.py
pycampbellcr1000/tests/ressources/__init__.py